{
  "generated_at": "2026-06-16T10:23:22.831363+00:00",
  "latest_date": "2026-06-15",
  "provider": "flow_positioning_proxy",
  "sources": {
    "DIA": {
      "latest_date": "2026-06-15",
      "missing_data": false,
      "real_data": true,
      "row_count": 520,
      "source": "yahoo-chart",
      "symbol": "DIA"
    },
    "HYG": {
      "latest_date": "2026-06-15",
      "missing_data": false,
      "real_data": true,
      "row_count": 520,
      "source": "local-cache-finnhub-quote-patch",
      "symbol": "HYG"
    },
    "IWM": {
      "latest_date": "2026-06-15",
      "missing_data": false,
      "real_data": true,
      "row_count": 520,
      "source": "yahoo-chart",
      "symbol": "IWM"
    },
    "QQQ": {
      "latest_date": "2026-06-15",
      "missing_data": false,
      "real_data": true,
      "row_count": 520,
      "source": "yahoo-chart",
      "symbol": "QQQ"
    },
    "RSP": {
      "latest_date": "2026-06-15",
      "missing_data": false,
      "real_data": true,
      "row_count": 520,
      "source": "finnhub-quote-patch",
      "symbol": "RSP"
    },
    "SPHB": {
      "latest_date": "2026-06-15",
      "missing_data": false,
      "real_data": true,
      "row_count": 520,
      "source": "finnhub-quote-patch",
      "symbol": "SPHB"
    },
    "SPLV": {
      "latest_date": "2026-06-15",
      "missing_data": false,
      "real_data": true,
      "row_count": 520,
      "source": "finnhub-quote-patch",
      "symbol": "SPLV"
    },
    "SPY": {
      "latest_date": "2026-06-15",
      "missing_data": false,
      "real_data": true,
      "row_count": 520,
      "source": "local-cache-finnhub-quote-patch",
      "symbol": "SPY"
    },
    "TLT": {
      "latest_date": "2026-06-15",
      "missing_data": false,
      "real_data": true,
      "row_count": 520,
      "source": "yahoo-chart",
      "symbol": "TLT"
    },
    "UUP": {
      "latest_date": "2026-06-15",
      "missing_data": false,
      "real_data": true,
      "row_count": 520,
      "source": "local-cache-finnhub-quote-patch",
      "symbol": "UUP"
    },
    "XLB": {
      "latest_date": "2026-06-15",
      "missing_data": false,
      "real_data": true,
      "row_count": 520,
      "source": "finnhub-quote-patch",
      "symbol": "XLB"
    },
    "XLC": {
      "latest_date": "2026-06-15",
      "missing_data": false,
      "real_data": true,
      "row_count": 520,
      "source": "yahoo-chart",
      "symbol": "XLC"
    },
    "XLE": {
      "latest_date": "2026-06-15",
      "missing_data": false,
      "real_data": true,
      "row_count": 520,
      "source": "finnhub-quote-patch",
      "symbol": "XLE"
    },
    "XLF": {
      "latest_date": "2026-06-15",
      "missing_data": false,
      "real_data": true,
      "row_count": 520,
      "source": "finnhub-quote-patch",
      "symbol": "XLF"
    },
    "XLI": {
      "latest_date": "2026-06-15",
      "missing_data": false,
      "real_data": true,
      "row_count": 520,
      "source": "finnhub-quote-patch",
      "symbol": "XLI"
    },
    "XLK": {
      "latest_date": "2026-06-15",
      "missing_data": false,
      "real_data": true,
      "row_count": 520,
      "source": "finnhub-quote-patch",
      "symbol": "XLK"
    },
    "XLP": {
      "latest_date": "2026-06-15",
      "missing_data": false,
      "real_data": true,
      "row_count": 520,
      "source": "finnhub-quote-patch",
      "symbol": "XLP"
    },
    "XLRE": {
      "latest_date": "2026-06-15",
      "missing_data": false,
      "real_data": true,
      "row_count": 520,
      "source": "yahoo-chart",
      "symbol": "XLRE"
    },
    "XLU": {
      "latest_date": "2026-06-15",
      "missing_data": false,
      "real_data": true,
      "row_count": 520,
      "source": "finnhub-quote-patch",
      "symbol": "XLU"
    },
    "XLV": {
      "latest_date": "2026-06-15",
      "missing_data": false,
      "real_data": true,
      "row_count": 520,
      "source": "finnhub-quote-patch",
      "symbol": "XLV"
    },
    "XLY": {
      "latest_date": "2026-06-15",
      "missing_data": false,
      "real_data": true,
      "row_count": 520,
      "source": "finnhub-quote-patch",
      "symbol": "XLY"
    }
  },
  "summary": {
    "average_flow_quality_score": 100.0,
    "data_note": "Flow is proxy-only and must be validated against future forecast accuracy.",
    "flow_available": true,
    "flow_proxy_only": true,
    "flow_symbols": [
      "SPY",
      "QQQ",
      "IWM",
      "DIA"
    ],
    "missing_real_flow_feeds": [
      "ETF fund flow",
      "prime brokerage positioning",
      "CFTC positioning",
      "dealer gamma/option flow"
    ],
    "missing_symbols": [],
    "overall_flow_confirmation_score": 78.81,
    "overall_flow_conflict_score": 25.88,
    "proxy_only": true,
    "stale_data": false,
    "true_flow_available": false
  },
  "symbols": {
    "DIA": {
      "data_note": "Proxy only: ETF volume, factor rotation, sector rotation, HYG/LQD, TLT and UUP. No true fund-flow or positioning feed.",
      "is_proxy": true,
      "latest_date": "2026-06-15",
      "metrics": {
        "credit_risk_appetite_20d": -0.003177,
        "crowding_proxy_score": 0.0129,
        "cyclical_vs_defensive_20d": -0.017145,
        "defensive_vs_cyclical_20d": 0.017145,
        "equal_weight_vs_cap_weight_20d": 0.034976,
        "etf_relative_volume_20d": 0.983,
        "growth_vs_defensive_20d": 0.006874,
        "high_beta_vs_low_vol_20d": 0.090675,
        "hyg_lqd_relative_strength_20d": -0.003177,
        "hyg_tlt_relative_strength_20d": -0.017324,
        "iwm_spy_relative_strength_20d": 0.040197,
        "qqq_spy_relative_strength_20d": 0.028283,
        "relative_volume_20d": 0.983,
        "relative_volume_5d": 0.8665,
        "risk_on_rotation_20d": 0.039455,
        "sector_participation_proxy": 0.8182,
        "sector_rotation_proxy_20d": {
          "XLB": 0.043738,
          "XLC": -0.033511,
          "XLE": -0.065444,
          "XLF": 0.048141,
          "XLI": 0.042474,
          "XLK": 0.088109,
          "XLP": 0.009924,
          "XLRE": 0.040713,
          "XLU": 0.019831,
          "XLV": 0.053687,
          "XLY": 0.017506
        },
        "small_cap_vs_large_cap_20d": 0.040197,
        "spy_tlt_relative_strength_20d": -0.003437,
        "tlt_behavior_20d": 0.024623,
        "uup_behavior_20d": 0.007202,
        "volume_confirmation_score": 0.5873,
        "volume_z_score": -0.0857,
        "volume_zscore_20d": -0.0857
      },
      "missing_symbols": [],
      "proxy_only": true,
      "scores": {
        "crowding_proxy_score": 1.29,
        "flow_confirmation_score": 79.02,
        "flow_conflict_score": 25.88,
        "flow_quality_score": 100.0,
        "forced_selling_proxy": 17.78,
        "positioning_pressure_score": 11.88,
        "risk_off_flow_score": 38.1,
        "risk_on_flow_score": 100.0,
        "short_covering_proxy": 30.16
      },
      "source": "market_data_proxy",
      "stale_data": false,
      "status": "proxy",
      "symbol": "DIA",
      "true_flow_available": false
    },
    "IWM": {
      "data_note": "Proxy only: ETF volume, factor rotation, sector rotation, HYG/LQD, TLT and UUP. No true fund-flow or positioning feed.",
      "is_proxy": true,
      "latest_date": "2026-06-15",
      "metrics": {
        "credit_risk_appetite_20d": -0.003177,
        "crowding_proxy_score": 0.1263,
        "cyclical_vs_defensive_20d": -0.017145,
        "defensive_vs_cyclical_20d": 0.017145,
        "equal_weight_vs_cap_weight_20d": 0.034976,
        "etf_relative_volume_20d": 0.8009,
        "growth_vs_defensive_20d": 0.006874,
        "high_beta_vs_low_vol_20d": 0.090675,
        "hyg_lqd_relative_strength_20d": -0.003177,
        "hyg_tlt_relative_strength_20d": -0.017324,
        "iwm_spy_relative_strength_20d": 0.040197,
        "qqq_spy_relative_strength_20d": 0.028283,
        "relative_volume_20d": 0.8009,
        "relative_volume_5d": 0.6472,
        "risk_on_rotation_20d": 0.039455,
        "sector_participation_proxy": 0.8182,
        "sector_rotation_proxy_20d": {
          "XLB": 0.043738,
          "XLC": -0.033511,
          "XLE": -0.065444,
          "XLF": 0.048141,
          "XLI": 0.042474,
          "XLK": 0.088109,
          "XLP": 0.009924,
          "XLRE": 0.040713,
          "XLU": 0.019831,
          "XLV": 0.053687,
          "XLY": 0.017506
        },
        "small_cap_vs_large_cap_20d": 0.040197,
        "spy_tlt_relative_strength_20d": -0.003437,
        "tlt_behavior_20d": 0.024623,
        "uup_behavior_20d": 0.007202,
        "volume_confirmation_score": 0.5054,
        "volume_z_score": -0.8418,
        "volume_zscore_20d": -0.8418
      },
      "missing_symbols": [],
      "proxy_only": true,
      "scores": {
        "crowding_proxy_score": 12.63,
        "flow_confirmation_score": 77.38,
        "flow_conflict_score": 25.88,
        "flow_quality_score": 100.0,
        "forced_selling_proxy": 17.78,
        "positioning_pressure_score": 15.85,
        "risk_off_flow_score": 38.1,
        "risk_on_flow_score": 100.0,
        "short_covering_proxy": 37.49
      },
      "source": "market_data_proxy",
      "stale_data": false,
      "status": "proxy",
      "symbol": "IWM",
      "true_flow_available": false
    },
    "QQQ": {
      "data_note": "Proxy only: ETF volume, factor rotation, sector rotation, HYG/LQD, TLT and UUP. No true fund-flow or positioning feed.",
      "is_proxy": true,
      "latest_date": "2026-06-15",
      "metrics": {
        "credit_risk_appetite_20d": -0.003177,
        "crowding_proxy_score": 0.0122,
        "cyclical_vs_defensive_20d": -0.017145,
        "defensive_vs_cyclical_20d": 0.017145,
        "equal_weight_vs_cap_weight_20d": 0.034976,
        "etf_relative_volume_20d": 0.9624,
        "growth_vs_defensive_20d": 0.006874,
        "high_beta_vs_low_vol_20d": 0.090675,
        "hyg_lqd_relative_strength_20d": -0.003177,
        "hyg_tlt_relative_strength_20d": -0.017324,
        "iwm_spy_relative_strength_20d": 0.040197,
        "qqq_spy_relative_strength_20d": 0.028283,
        "relative_volume_20d": 0.9624,
        "relative_volume_5d": 0.71,
        "risk_on_rotation_20d": 0.039455,
        "sector_participation_proxy": 0.8182,
        "sector_rotation_proxy_20d": {
          "XLB": 0.043738,
          "XLC": -0.033511,
          "XLE": -0.065444,
          "XLF": 0.048141,
          "XLI": 0.042474,
          "XLK": 0.088109,
          "XLP": 0.009924,
          "XLRE": 0.040713,
          "XLU": 0.019831,
          "XLV": 0.053687,
          "XLY": 0.017506
        },
        "small_cap_vs_large_cap_20d": 0.040197,
        "spy_tlt_relative_strength_20d": -0.003437,
        "tlt_behavior_20d": 0.024623,
        "uup_behavior_20d": 0.007202,
        "volume_confirmation_score": 0.5781,
        "volume_z_score": -0.0813,
        "volume_zscore_20d": -0.0813
      },
      "missing_symbols": [],
      "proxy_only": true,
      "scores": {
        "crowding_proxy_score": 1.22,
        "flow_confirmation_score": 78.83,
        "flow_conflict_score": 25.88,
        "flow_quality_score": 100.0,
        "forced_selling_proxy": 17.78,
        "positioning_pressure_score": 11.86,
        "risk_off_flow_score": 38.1,
        "risk_on_flow_score": 100.0,
        "short_covering_proxy": 38.27
      },
      "source": "market_data_proxy",
      "stale_data": false,
      "status": "proxy",
      "symbol": "QQQ",
      "true_flow_available": false
    },
    "SPY": {
      "data_note": "Proxy only: ETF volume, factor rotation, sector rotation, HYG/LQD, TLT and UUP. No true fund-flow or positioning feed.",
      "is_proxy": true,
      "latest_date": "2026-06-15",
      "metrics": {
        "credit_risk_appetite_20d": -0.003177,
        "crowding_proxy_score": 0.0262,
        "cyclical_vs_defensive_20d": -0.017145,
        "defensive_vs_cyclical_20d": 0.017145,
        "equal_weight_vs_cap_weight_20d": 0.034976,
        "etf_relative_volume_20d": 1.0642,
        "growth_vs_defensive_20d": 0.006874,
        "high_beta_vs_low_vol_20d": 0.090675,
        "hyg_lqd_relative_strength_20d": -0.003177,
        "hyg_tlt_relative_strength_20d": -0.017324,
        "iwm_spy_relative_strength_20d": 0.040197,
        "qqq_spy_relative_strength_20d": 0.028283,
        "relative_volume_20d": 1.0642,
        "relative_volume_5d": 0.7557,
        "risk_on_rotation_20d": 0.039455,
        "sector_participation_proxy": 0.8182,
        "sector_rotation_proxy_20d": {
          "XLB": 0.043738,
          "XLC": -0.033511,
          "XLE": -0.065444,
          "XLF": 0.048141,
          "XLI": 0.042474,
          "XLK": 0.088109,
          "XLP": 0.009924,
          "XLRE": 0.040713,
          "XLU": 0.019831,
          "XLV": 0.053687,
          "XLY": 0.017506
        },
        "small_cap_vs_large_cap_20d": 0.040197,
        "spy_tlt_relative_strength_20d": -0.003437,
        "tlt_behavior_20d": 0.024623,
        "uup_behavior_20d": 0.007202,
        "volume_confirmation_score": 0.6378,
        "volume_z_score": 0.1743,
        "volume_zscore_20d": 0.1743
      },
      "missing_symbols": [],
      "proxy_only": true,
      "scores": {
        "crowding_proxy_score": 2.62,
        "flow_confirmation_score": 80.03,
        "flow_conflict_score": 25.88,
        "flow_quality_score": 100.0,
        "forced_selling_proxy": 17.78,
        "positioning_pressure_score": 12.34,
        "risk_off_flow_score": 38.1,
        "risk_on_flow_score": 100.0,
        "short_covering_proxy": 31.12
      },
      "source": "market_data_proxy",
      "stale_data": false,
      "status": "proxy",
      "symbol": "SPY",
      "true_flow_available": false
    }
  },
  "version": "v5_flow_positioning_proxy",
  "warnings": [
    "Flow / positioning is proxy-only. It uses ETF volume, relative volume, rotation, credit ETFs, rates ETFs and factor ETFs.",
    "No true fund-flow, prime brokerage, CFTC, dealer positioning or option-flow feed is connected.",
    "Proxy flow can improve information quality, but it is not proof of forecast accuracy."
  ]
}
