{
  "as_of": "2026-07-23",
  "disclaimer": "Forecast price levels are probabilistic scenario points derived from simulated paths, recent price structure and volatility bands. They are not execution instructions, risk-control rules, or guaranteed target prices.",
  "generated_at": "2026-07-23T22:35:57.063270Z",
  "symbols": {
    "DIA": {
      "current_price": 516.260009765625,
      "forecast_price_table": {
        "10d": {
          "analog_average_price": 515.72,
          "confidence_level": "low",
          "expected_price": 516.74,
          "expected_return": 0.0009,
          "horizon": "10d",
          "lower_confidence_price": 507.1,
          "not_guaranteed_forecast": true,
          "primary_scenario": "bearish_path",
          "primary_scenario_label": "风险路径",
          "primary_scenario_price": 507.1,
          "probability_of_reaching_primary_price": 0.3322,
          "risk_scenario": "bearish_path",
          "risk_scenario_label": "风险路径",
          "risk_scenario_price": 507.1,
          "secondary_scenario": "bounce_path",
          "secondary_scenario_label": "反抽情景",
          "secondary_scenario_price": 521.57,
          "source": "simulated_path",
          "upper_confidence_price": 521.57
        },
        "1d": {
          "analog_average_price": 514.08,
          "confidence_level": "low",
          "expected_price": 512.73,
          "expected_return": -0.0068,
          "horizon": "1d",
          "lower_confidence_price": 509.96,
          "not_guaranteed_forecast": true,
          "primary_scenario": "bearish_path",
          "primary_scenario_label": "风险路径",
          "primary_scenario_price": 509.96,
          "probability_of_reaching_primary_price": 0.3322,
          "risk_scenario": "bearish_path",
          "risk_scenario_label": "风险路径",
          "risk_scenario_price": 509.96,
          "secondary_scenario": "bounce_path",
          "secondary_scenario_label": "反抽情景",
          "secondary_scenario_price": 516.55,
          "source": "simulated_path",
          "upper_confidence_price": 516.55
        },
        "20d": {
          "analog_average_price": 521.73,
          "confidence_level": "low",
          "expected_price": 526.93,
          "expected_return": 0.0207,
          "horizon": "20d",
          "lower_confidence_price": 495.23,
          "not_guaranteed_forecast": true,
          "primary_scenario": "bearish_path",
          "primary_scenario_label": "风险路径",
          "primary_scenario_price": 495.23,
          "probability_of_reaching_primary_price": 0.3322,
          "risk_scenario": "bearish_path",
          "risk_scenario_label": "风险路径",
          "risk_scenario_price": 495.23,
          "secondary_scenario": "bounce_path",
          "secondary_scenario_label": "反抽情景",
          "secondary_scenario_price": 543.05,
          "source": "simulated_path",
          "upper_confidence_price": 543.05
        },
        "3d": {
          "analog_average_price": 515.52,
          "confidence_level": "low",
          "expected_price": 516.22,
          "expected_return": -0.0001,
          "horizon": "3d",
          "lower_confidence_price": 509.44,
          "not_guaranteed_forecast": true,
          "primary_scenario": "bearish_path",
          "primary_scenario_label": "风险路径",
          "primary_scenario_price": 509.44,
          "probability_of_reaching_primary_price": 0.3322,
          "risk_scenario": "bearish_path",
          "risk_scenario_label": "风险路径",
          "risk_scenario_price": 509.44,
          "secondary_scenario": "bounce_path",
          "secondary_scenario_label": "反抽情景",
          "secondary_scenario_price": 520.81,
          "source": "simulated_path",
          "upper_confidence_price": 520.81
        },
        "5d": {
          "analog_average_price": 516.27,
          "confidence_level": "low",
          "expected_price": 518.64,
          "expected_return": 0.0046,
          "horizon": "5d",
          "lower_confidence_price": 510.32,
          "not_guaranteed_forecast": true,
          "primary_scenario": "bearish_path",
          "primary_scenario_label": "风险路径",
          "primary_scenario_price": 510.32,
          "probability_of_reaching_primary_price": 0.3322,
          "risk_scenario": "bearish_path",
          "risk_scenario_label": "风险路径",
          "risk_scenario_price": 510.32,
          "secondary_scenario": "bounce_path",
          "secondary_scenario_label": "反抽情景",
          "secondary_scenario_price": 523.0,
          "source": "simulated_path",
          "upper_confidence_price": 523.0
        },
        "60d": {
          "analog_average_price": 528.22,
          "confidence_level": "low",
          "expected_price": 535.67,
          "expected_return": 0.0376,
          "horizon": "60d",
          "lower_confidence_price": 503.84,
          "not_guaranteed_forecast": true,
          "primary_scenario": "bearish_path",
          "primary_scenario_label": "风险路径",
          "primary_scenario_price": 503.84,
          "probability_of_reaching_primary_price": 0.3322,
          "risk_scenario": "bearish_path",
          "risk_scenario_label": "风险路径",
          "risk_scenario_price": 503.84,
          "secondary_scenario": "bounce_path",
          "secondary_scenario_label": "反抽情景",
          "secondary_scenario_price": 552.17,
          "source": "simulated_path",
          "upper_confidence_price": 552.17
        }
      },
      "horizon_prices": {
        "10d": {
          "analog_average_price": 515.72,
          "confidence": "low",
          "expected_price": 516.74,
          "expected_return": 0.0009,
          "lower_confidence_price": 507.1,
          "not_guaranteed_forecast": true,
          "primary_scenario_price": 507.1,
          "probability_of_reaching_primary_price": 0.3322,
          "risk_scenario_price": 507.1,
          "secondary_scenario_price": 521.57,
          "source": "simulated_path",
          "upper_confidence_price": 521.57
        },
        "1d": {
          "analog_average_price": 514.08,
          "confidence": "low",
          "expected_price": 512.73,
          "expected_return": -0.0068,
          "lower_confidence_price": 509.96,
          "not_guaranteed_forecast": true,
          "primary_scenario_price": 509.96,
          "probability_of_reaching_primary_price": 0.3322,
          "risk_scenario_price": 509.96,
          "secondary_scenario_price": 516.55,
          "source": "simulated_path",
          "upper_confidence_price": 516.55
        },
        "20d": {
          "analog_average_price": 521.73,
          "confidence": "low",
          "expected_price": 526.93,
          "expected_return": 0.0207,
          "lower_confidence_price": 495.23,
          "not_guaranteed_forecast": true,
          "primary_scenario_price": 495.23,
          "probability_of_reaching_primary_price": 0.3322,
          "risk_scenario_price": 495.23,
          "secondary_scenario_price": 543.05,
          "source": "simulated_path",
          "upper_confidence_price": 543.05
        },
        "3d": {
          "analog_average_price": 515.52,
          "confidence": "low",
          "expected_price": 516.22,
          "expected_return": -0.0001,
          "lower_confidence_price": 509.44,
          "not_guaranteed_forecast": true,
          "primary_scenario_price": 509.44,
          "probability_of_reaching_primary_price": 0.3322,
          "risk_scenario_price": 509.44,
          "secondary_scenario_price": 520.81,
          "source": "simulated_path",
          "upper_confidence_price": 520.81
        },
        "5d": {
          "analog_average_price": 516.27,
          "confidence": "low",
          "expected_price": 518.64,
          "expected_return": 0.0046,
          "lower_confidence_price": 510.32,
          "not_guaranteed_forecast": true,
          "primary_scenario_price": 510.32,
          "probability_of_reaching_primary_price": 0.3322,
          "risk_scenario_price": 510.32,
          "secondary_scenario_price": 523.0,
          "source": "simulated_path",
          "upper_confidence_price": 523.0
        },
        "60d": {
          "analog_average_price": 528.22,
          "confidence": "low",
          "expected_price": 535.67,
          "expected_return": 0.0376,
          "lower_confidence_price": 503.84,
          "not_guaranteed_forecast": true,
          "primary_scenario_price": 503.84,
          "probability_of_reaching_primary_price": 0.3322,
          "risk_scenario_price": 503.84,
          "secondary_scenario_price": 552.17,
          "source": "simulated_path",
          "upper_confidence_price": 552.17
        }
      },
      "name": "Dow Jones",
      "not_trading_advice": true,
      "path_trigger_levels": {
        "bounce_target_zone": {
          "base_bounce_target": {
            "condition": "基础反抽情景点位，主要来自 20d 反抽路径。",
            "distance_from_current": 26.79,
            "distance_percent": 0.0519,
            "inputs": [
              "bounce_path_20d",
              "primary_path_20d",
              "recent_20d_high"
            ],
            "not_trading_advice": true,
            "price": 543.05,
            "source": "simulated_path"
          },
          "conservative_bounce_target": {
            "condition": "保守反抽情景点位，来自短期反抽路径和近期压力区。",
            "distance_from_current": 6.74,
            "distance_percent": 0.0131,
            "inputs": [
              "bounce_path_5d",
              "recent_5d_high"
            ],
            "not_trading_advice": true,
            "price": 523.0,
            "source": "confluence"
          },
          "extended_bounce_target": {
            "condition": "扩展反抽情景点位，来自 60d 反抽路径或上方置信带。",
            "distance_from_current": 35.91,
            "distance_percent": 0.0696,
            "inputs": [
              "bounce_path_60d",
              "upper_confidence_band_20d"
            ],
            "not_trading_advice": true,
            "price": 552.17,
            "source": "simulated_path"
          }
        },
        "calculation_note": "Levels are derived from simulated paths, recent price structure, realized-volatility bands and scenario probabilities. They are not trading instructions.",
        "current_price": 516.26,
        "failed_bounce_warning_zone": {
          "critical_warning_level": {
            "condition": "关键警戒区：跌破后风险路径权重显著上升。",
            "distance_from_current": -21.03,
            "distance_percent": -0.0407,
            "inputs": [
              "recent_20d_low",
              "risk_path_10d",
              "lower_confidence_band_20d"
            ],
            "not_trading_advice": true,
            "price": 495.23,
            "source": "simulated_path"
          },
          "first_warning_level": {
            "condition": "第一警戒区：跌破后说明反抽质量变差。",
            "distance_from_current": -6.82,
            "distance_percent": -0.0132,
            "inputs": [
              "recent_5d_low",
              "lower_confidence_band_3d"
            ],
            "not_trading_advice": true,
            "price": 509.44,
            "source": "price_structure"
          }
        },
        "primary_confirmation_level": {
          "condition": "若价格突破或收在该价位上方，说明主路径正在兑现；这不是操作建议。",
          "distance_from_current": 5.25,
          "distance_percent": 0.0102,
          "inputs": [
            "primary_path_5d",
            "recent_5d_high",
            "realized_volatility_band"
          ],
          "not_trading_advice": true,
          "price": 521.51,
          "source": "simulated_path"
        },
        "primary_invalidation_level": {
          "condition": "若价格跌破或收在该价位下方，主路径可信度下降，风险路径权重上升。",
          "distance_from_current": -6.82,
          "distance_percent": -0.0132,
          "inputs": [
            "recent_10d_low",
            "lower_confidence_band_3d",
            "realized_volatility_band"
          ],
          "not_trading_advice": true,
          "price": 509.44,
          "source": "price_structure"
        },
        "primary_probability": 0.3322,
        "primary_scenario": "bearish_path",
        "probability_gap": 0.0756,
        "risk_probability": 0.2425,
        "risk_scenario_activation_level": {
          "condition": "若价格跌破该价位，失败反抽 / 下跌延续路径开始接管。",
          "distance_from_current": -21.03,
          "distance_percent": -0.0407,
          "inputs": [
            "risk_path_10d",
            "recent_20d_low",
            "lower_confidence_band_20d"
          ],
          "not_trading_advice": true,
          "price": 495.23,
          "source": "simulated_path"
        },
        "secondary_probability": 0.2566,
        "trend_reversal_confirmation_level": {
          "condition": "若价格突破该价位，趋势修复概率上升；仍需后续前向验证。",
          "distance_from_current": 13.83,
          "distance_percent": 0.0268,
          "inputs": [
            "primary_path_20d",
            "recent_20d_high",
            "20d_or_50d_moving_average"
          ],
          "not_trading_advice": true,
          "price": 530.09,
          "source": "price_structure"
        }
      },
      "price_structure": {
        "atr_proxy_14d": 2.26,
        "data_points": 260,
        "high_10d": 525.95,
        "high_20d": 530.09,
        "high_5d": 521.51,
        "latest_date": "2026-07-23",
        "low_10d": 516.26,
        "low_20d": 516.26,
        "low_5d": 516.26,
        "ma_200d": 488.86,
        "ma_200d_status": "available",
        "ma_20d": 523.03,
        "ma_50d": 514.15,
        "realized_volatility_20d": 0.0886,
        "source": "price_structure",
        "status": "available"
      },
      "primary_probability": 0.3322,
      "primary_scenario": "bearish_path",
      "risk_probability": 0.2425,
      "risk_scenario": "analog_average_path",
      "secondary_probability": 0.2566,
      "secondary_scenario": "bounce_path",
      "source_note": "Derived from existing simulated paths, recent price structure and realized-volatility bands.",
      "summary": {
        "plain_language": "DIA 当前主路径是 失败反抽情景，第二路径是 反抽情景。价格点位只是路径验证条件，不是操作建议。",
        "primary_confirmation_distance": {
          "distance_from_current": 5.25,
          "distance_percent": 0.0102,
          "price": 521.51
        },
        "primary_invalidation_distance": {
          "distance_from_current": -6.82,
          "distance_percent": -0.0132,
          "price": 509.44
        },
        "risk_activation_distance": {
          "distance_from_current": -21.03,
          "distance_percent": -0.0407,
          "price": 495.23
        }
      },
      "symbol": "DIA",
      "trigger_levels": {
        "bounce_target_zone": {
          "base": 543.05,
          "conservative": 523.0,
          "extended": 552.17
        },
        "failed_bounce_warning_zone": {
          "critical_warning": 495.23,
          "first_warning": 509.44
        },
        "not_trading_advice": true,
        "primary_confirmation_level": {
          "confidence": "medium",
          "distance_pct": 0.0102,
          "meaning": "若价格突破或收在该价位上方，说明主路径正在兑现；这不是操作建议。",
          "price": 521.51,
          "source": "primary_path_5d + recent_5d_high + realized_volatility_band",
          "source_type": "simulated_path"
        },
        "primary_invalidation_level": {
          "confidence": "medium",
          "distance_pct": -0.0132,
          "meaning": "若价格跌破或收在该价位下方，主路径可信度下降，风险路径权重上升。",
          "price": 509.44,
          "source": "recent_10d_low + lower_confidence_band_3d + realized_volatility_band",
          "source_type": "price_structure"
        },
        "risk_scenario_activation_level": {
          "confidence": "medium",
          "distance_pct": -0.0407,
          "meaning": "若价格跌破该价位，失败反抽 / 下跌延续路径开始接管。",
          "price": 495.23,
          "source": "risk_path_10d + recent_20d_low + lower_confidence_band_20d",
          "source_type": "simulated_path"
        },
        "trend_reversal_confirmation_level": {
          "confidence": "medium",
          "distance_pct": 0.0268,
          "meaning": "若价格突破该价位，趋势修复概率上升；仍需后续前向验证。",
          "price": 530.09,
          "source": "primary_path_20d + recent_20d_high + 20d_or_50d_moving_average",
          "source_type": "price_structure"
        }
      }
    },
    "IWM": {
      "current_price": 292.0899963378906,
      "forecast_price_table": {
        "10d": {
          "analog_average_price": 292.21,
          "confidence_level": "low",
          "expected_price": 293.09,
          "expected_return": 0.0034,
          "horizon": "10d",
          "lower_confidence_price": 279.64,
          "not_guaranteed_forecast": true,
          "primary_scenario": "bearish_path",
          "primary_scenario_label": "风险路径",
          "primary_scenario_price": 279.64,
          "probability_of_reaching_primary_price": 0.417,
          "risk_scenario": "bearish_path",
          "risk_scenario_label": "风险路径",
          "risk_scenario_price": 279.64,
          "secondary_scenario": "analog_average_path",
          "secondary_scenario_label": "历史均值情景",
          "secondary_scenario_price": 292.21,
          "source": "simulated_path",
          "upper_confidence_price": 300.48
        },
        "1d": {
          "analog_average_price": 290.41,
          "confidence_level": "low",
          "expected_price": 289.59,
          "expected_return": -0.0085,
          "horizon": "1d",
          "lower_confidence_price": 286.86,
          "not_guaranteed_forecast": true,
          "primary_scenario": "bearish_path",
          "primary_scenario_label": "风险路径",
          "primary_scenario_price": 286.86,
          "probability_of_reaching_primary_price": 0.417,
          "risk_scenario": "bearish_path",
          "risk_scenario_label": "风险路径",
          "risk_scenario_price": 286.86,
          "secondary_scenario": "analog_average_path",
          "secondary_scenario_label": "历史均值情景",
          "secondary_scenario_price": 290.41,
          "source": "simulated_path",
          "upper_confidence_price": 292.44
        },
        "20d": {
          "analog_average_price": 292.61,
          "confidence_level": "low",
          "expected_price": 297.08,
          "expected_return": 0.0171,
          "horizon": "20d",
          "lower_confidence_price": 265.67,
          "not_guaranteed_forecast": true,
          "primary_scenario": "bearish_path",
          "primary_scenario_label": "风险路径",
          "primary_scenario_price": 265.67,
          "probability_of_reaching_primary_price": 0.417,
          "risk_scenario": "bearish_path",
          "risk_scenario_label": "风险路径",
          "risk_scenario_price": 265.67,
          "secondary_scenario": "analog_average_path",
          "secondary_scenario_label": "历史均值情景",
          "secondary_scenario_price": 292.61,
          "source": "simulated_path",
          "upper_confidence_price": 314.66
        },
        "3d": {
          "analog_average_price": 290.32,
          "confidence_level": "low",
          "expected_price": 290.56,
          "expected_return": -0.0052,
          "horizon": "3d",
          "lower_confidence_price": 283.21,
          "not_guaranteed_forecast": true,
          "primary_scenario": "bearish_path",
          "primary_scenario_label": "风险路径",
          "primary_scenario_price": 283.21,
          "probability_of_reaching_primary_price": 0.417,
          "risk_scenario": "bearish_path",
          "risk_scenario_label": "风险路径",
          "risk_scenario_price": 283.21,
          "secondary_scenario": "analog_average_path",
          "secondary_scenario_label": "历史均值情景",
          "secondary_scenario_price": 290.32,
          "source": "simulated_path",
          "upper_confidence_price": 295.23
        },
        "5d": {
          "analog_average_price": 289.23,
          "confidence_level": "low",
          "expected_price": 290.69,
          "expected_return": -0.0048,
          "horizon": "5d",
          "lower_confidence_price": 279.47,
          "not_guaranteed_forecast": true,
          "primary_scenario": "bearish_path",
          "primary_scenario_label": "风险路径",
          "primary_scenario_price": 279.47,
          "probability_of_reaching_primary_price": 0.417,
          "risk_scenario": "bearish_path",
          "risk_scenario_label": "风险路径",
          "risk_scenario_price": 279.47,
          "secondary_scenario": "analog_average_path",
          "secondary_scenario_label": "历史均值情景",
          "secondary_scenario_price": 289.23,
          "source": "simulated_path",
          "upper_confidence_price": 296.95
        },
        "60d": {
          "analog_average_price": 290.76,
          "confidence_level": "low",
          "expected_price": 288.83,
          "expected_return": -0.0112,
          "horizon": "60d",
          "lower_confidence_price": 246.51,
          "not_guaranteed_forecast": true,
          "primary_scenario": "bearish_path",
          "primary_scenario_label": "风险路径",
          "primary_scenario_price": 246.51,
          "probability_of_reaching_primary_price": 0.417,
          "risk_scenario": "bearish_path",
          "risk_scenario_label": "风险路径",
          "risk_scenario_price": 246.51,
          "secondary_scenario": "analog_average_path",
          "secondary_scenario_label": "历史均值情景",
          "secondary_scenario_price": 290.76,
          "source": "simulated_path",
          "upper_confidence_price": 311.38
        }
      },
      "horizon_prices": {
        "10d": {
          "analog_average_price": 292.21,
          "confidence": "low",
          "expected_price": 293.09,
          "expected_return": 0.0034,
          "lower_confidence_price": 279.64,
          "not_guaranteed_forecast": true,
          "primary_scenario_price": 279.64,
          "probability_of_reaching_primary_price": 0.417,
          "risk_scenario_price": 279.64,
          "secondary_scenario_price": 292.21,
          "source": "simulated_path",
          "upper_confidence_price": 300.48
        },
        "1d": {
          "analog_average_price": 290.41,
          "confidence": "low",
          "expected_price": 289.59,
          "expected_return": -0.0085,
          "lower_confidence_price": 286.86,
          "not_guaranteed_forecast": true,
          "primary_scenario_price": 286.86,
          "probability_of_reaching_primary_price": 0.417,
          "risk_scenario_price": 286.86,
          "secondary_scenario_price": 290.41,
          "source": "simulated_path",
          "upper_confidence_price": 292.44
        },
        "20d": {
          "analog_average_price": 292.61,
          "confidence": "low",
          "expected_price": 297.08,
          "expected_return": 0.0171,
          "lower_confidence_price": 265.67,
          "not_guaranteed_forecast": true,
          "primary_scenario_price": 265.67,
          "probability_of_reaching_primary_price": 0.417,
          "risk_scenario_price": 265.67,
          "secondary_scenario_price": 292.61,
          "source": "simulated_path",
          "upper_confidence_price": 314.66
        },
        "3d": {
          "analog_average_price": 290.32,
          "confidence": "low",
          "expected_price": 290.56,
          "expected_return": -0.0052,
          "lower_confidence_price": 283.21,
          "not_guaranteed_forecast": true,
          "primary_scenario_price": 283.21,
          "probability_of_reaching_primary_price": 0.417,
          "risk_scenario_price": 283.21,
          "secondary_scenario_price": 290.32,
          "source": "simulated_path",
          "upper_confidence_price": 295.23
        },
        "5d": {
          "analog_average_price": 289.23,
          "confidence": "low",
          "expected_price": 290.69,
          "expected_return": -0.0048,
          "lower_confidence_price": 279.47,
          "not_guaranteed_forecast": true,
          "primary_scenario_price": 279.47,
          "probability_of_reaching_primary_price": 0.417,
          "risk_scenario_price": 279.47,
          "secondary_scenario_price": 289.23,
          "source": "simulated_path",
          "upper_confidence_price": 296.95
        },
        "60d": {
          "analog_average_price": 290.76,
          "confidence": "low",
          "expected_price": 288.83,
          "expected_return": -0.0112,
          "lower_confidence_price": 246.51,
          "not_guaranteed_forecast": true,
          "primary_scenario_price": 246.51,
          "probability_of_reaching_primary_price": 0.417,
          "risk_scenario_price": 246.51,
          "secondary_scenario_price": 290.76,
          "source": "simulated_path",
          "upper_confidence_price": 311.38
        }
      },
      "name": "Russell 2000",
      "not_trading_advice": true,
      "path_trigger_levels": {
        "bounce_target_zone": {
          "base_bounce_target": {
            "condition": "基础反抽情景点位，主要来自 20d 反抽路径。",
            "distance_from_current": 22.57,
            "distance_percent": 0.0773,
            "inputs": [
              "bounce_path_20d",
              "primary_path_20d",
              "recent_20d_high"
            ],
            "not_trading_advice": true,
            "price": 314.66,
            "source": "simulated_path"
          },
          "conservative_bounce_target": {
            "condition": "保守反抽情景点位，来自短期反抽路径和近期压力区。",
            "distance_from_current": 4.86,
            "distance_percent": 0.0167,
            "inputs": [
              "bounce_path_5d",
              "recent_5d_high"
            ],
            "not_trading_advice": true,
            "price": 296.95,
            "source": "confluence"
          },
          "extended_bounce_target": {
            "condition": "扩展反抽情景点位，来自 60d 反抽路径或上方置信带。",
            "distance_from_current": 22.57,
            "distance_percent": 0.0773,
            "inputs": [
              "bounce_path_60d",
              "upper_confidence_band_20d"
            ],
            "not_trading_advice": true,
            "price": 314.66,
            "source": "volatility_band"
          }
        },
        "calculation_note": "Levels are derived from simulated paths, recent price structure, realized-volatility bands and scenario probabilities. They are not trading instructions.",
        "current_price": 292.09,
        "failed_bounce_warning_zone": {
          "critical_warning_level": {
            "condition": "关键警戒区：跌破后风险路径权重显著上升。",
            "distance_from_current": -26.42,
            "distance_percent": -0.0905,
            "inputs": [
              "recent_20d_low",
              "risk_path_10d",
              "lower_confidence_band_20d"
            ],
            "not_trading_advice": true,
            "price": 265.67,
            "source": "simulated_path"
          },
          "first_warning_level": {
            "condition": "第一警戒区：跌破后说明反抽质量变差。",
            "distance_from_current": -8.88,
            "distance_percent": -0.0304,
            "inputs": [
              "recent_5d_low",
              "lower_confidence_band_3d"
            ],
            "not_trading_advice": true,
            "price": 283.21,
            "source": "price_structure"
          }
        },
        "primary_confirmation_level": {
          "condition": "若价格突破或收在该价位上方，说明主路径正在兑现；这不是操作建议。",
          "distance_from_current": 4.45,
          "distance_percent": 0.0152,
          "inputs": [
            "primary_path_5d",
            "recent_5d_high",
            "realized_volatility_band"
          ],
          "not_trading_advice": true,
          "price": 296.54,
          "source": "simulated_path"
        },
        "primary_invalidation_level": {
          "condition": "若价格跌破或收在该价位下方，主路径可信度下降，风险路径权重上升。",
          "distance_from_current": -8.88,
          "distance_percent": -0.0304,
          "inputs": [
            "recent_10d_low",
            "lower_confidence_band_3d",
            "realized_volatility_band"
          ],
          "not_trading_advice": true,
          "price": 283.21,
          "source": "price_structure"
        },
        "primary_probability": 0.417,
        "primary_scenario": "bearish_path",
        "probability_gap": 0.2107,
        "risk_probability": 0.1988,
        "risk_scenario_activation_level": {
          "condition": "若价格跌破该价位，失败反抽 / 下跌延续路径开始接管。",
          "distance_from_current": -26.42,
          "distance_percent": -0.0905,
          "inputs": [
            "risk_path_10d",
            "recent_20d_low",
            "lower_confidence_band_20d"
          ],
          "not_trading_advice": true,
          "price": 265.67,
          "source": "simulated_path"
        },
        "secondary_probability": 0.2063,
        "trend_reversal_confirmation_level": {
          "condition": "若价格突破该价位，趋势修复概率上升；仍需后续前向验证。",
          "distance_from_current": 8.36,
          "distance_percent": 0.0286,
          "inputs": [
            "primary_path_20d",
            "recent_20d_high",
            "20d_or_50d_moving_average"
          ],
          "not_trading_advice": true,
          "price": 300.45,
          "source": "price_structure"
        }
      },
      "price_structure": {
        "atr_proxy_14d": 2.03,
        "data_points": 260,
        "high_10d": 296.54,
        "high_20d": 300.45,
        "high_5d": 296.54,
        "latest_date": "2026-07-23",
        "low_10d": 292.09,
        "low_20d": 292.09,
        "low_5d": 292.09,
        "ma_200d": 264.43,
        "ma_200d_status": "available",
        "ma_20d": 296.25,
        "ma_50d": 291.02,
        "realized_volatility_20d": 0.1149,
        "source": "price_structure",
        "status": "available"
      },
      "primary_probability": 0.417,
      "primary_scenario": "bearish_path",
      "risk_probability": 0.1988,
      "risk_scenario": "bounce_path",
      "secondary_probability": 0.2063,
      "secondary_scenario": "analog_average_path",
      "source_note": "Derived from existing simulated paths, recent price structure and realized-volatility bands.",
      "summary": {
        "plain_language": "IWM 当前主路径是 失败反抽情景，第二路径是 历史均值情景。价格点位只是路径验证条件，不是操作建议。",
        "primary_confirmation_distance": {
          "distance_from_current": 4.45,
          "distance_percent": 0.0152,
          "price": 296.54
        },
        "primary_invalidation_distance": {
          "distance_from_current": -8.88,
          "distance_percent": -0.0304,
          "price": 283.21
        },
        "risk_activation_distance": {
          "distance_from_current": -26.42,
          "distance_percent": -0.0905,
          "price": 265.67
        }
      },
      "symbol": "IWM",
      "trigger_levels": {
        "bounce_target_zone": {
          "base": 314.66,
          "conservative": 296.95,
          "extended": 314.66
        },
        "failed_bounce_warning_zone": {
          "critical_warning": 265.67,
          "first_warning": 283.21
        },
        "not_trading_advice": true,
        "primary_confirmation_level": {
          "confidence": "medium",
          "distance_pct": 0.0152,
          "meaning": "若价格突破或收在该价位上方，说明主路径正在兑现；这不是操作建议。",
          "price": 296.54,
          "source": "primary_path_5d + recent_5d_high + realized_volatility_band",
          "source_type": "simulated_path"
        },
        "primary_invalidation_level": {
          "confidence": "medium",
          "distance_pct": -0.0304,
          "meaning": "若价格跌破或收在该价位下方，主路径可信度下降，风险路径权重上升。",
          "price": 283.21,
          "source": "recent_10d_low + lower_confidence_band_3d + realized_volatility_band",
          "source_type": "price_structure"
        },
        "risk_scenario_activation_level": {
          "confidence": "medium",
          "distance_pct": -0.0905,
          "meaning": "若价格跌破该价位，失败反抽 / 下跌延续路径开始接管。",
          "price": 265.67,
          "source": "risk_path_10d + recent_20d_low + lower_confidence_band_20d",
          "source_type": "simulated_path"
        },
        "trend_reversal_confirmation_level": {
          "confidence": "medium",
          "distance_pct": 0.0286,
          "meaning": "若价格突破该价位，趋势修复概率上升；仍需后续前向验证。",
          "price": 300.45,
          "source": "primary_path_20d + recent_20d_high + 20d_or_50d_moving_average",
          "source_type": "price_structure"
        }
      }
    },
    "QQQ": {
      "current_price": 691.9600219726562,
      "forecast_price_table": {
        "10d": {
          "analog_average_price": 712.61,
          "confidence_level": "low",
          "expected_price": 719.47,
          "expected_return": 0.0398,
          "horizon": "10d",
          "lower_confidence_price": 691.73,
          "not_guaranteed_forecast": true,
          "primary_scenario": "bearish_path",
          "primary_scenario_label": "风险路径",
          "primary_scenario_price": 691.73,
          "probability_of_reaching_primary_price": 0.3654,
          "risk_scenario": "bearish_path",
          "risk_scenario_label": "风险路径",
          "risk_scenario_price": 691.73,
          "secondary_scenario": "analog_average_path",
          "secondary_scenario_label": "历史均值情景",
          "secondary_scenario_price": 712.61,
          "source": "simulated_path",
          "upper_confidence_price": 733.02
        },
        "1d": {
          "analog_average_price": 689.48,
          "confidence_level": "low",
          "expected_price": 687.21,
          "expected_return": -0.0069,
          "horizon": "1d",
          "lower_confidence_price": 680.28,
          "not_guaranteed_forecast": true,
          "primary_scenario": "bearish_path",
          "primary_scenario_label": "风险路径",
          "primary_scenario_price": 680.28,
          "probability_of_reaching_primary_price": 0.3654,
          "risk_scenario": "bearish_path",
          "risk_scenario_label": "风险路径",
          "risk_scenario_price": 680.28,
          "secondary_scenario": "analog_average_path",
          "secondary_scenario_label": "历史均值情景",
          "secondary_scenario_price": 689.48,
          "source": "simulated_path",
          "upper_confidence_price": 693.63
        },
        "20d": {
          "analog_average_price": 726.24,
          "confidence_level": "low",
          "expected_price": 737.24,
          "expected_return": 0.0654,
          "horizon": "20d",
          "lower_confidence_price": 684.75,
          "not_guaranteed_forecast": true,
          "primary_scenario": "bearish_path",
          "primary_scenario_label": "风险路径",
          "primary_scenario_price": 684.75,
          "probability_of_reaching_primary_price": 0.3654,
          "risk_scenario": "bearish_path",
          "risk_scenario_label": "风险路径",
          "risk_scenario_price": 684.75,
          "secondary_scenario": "analog_average_path",
          "secondary_scenario_label": "历史均值情景",
          "secondary_scenario_price": 726.24,
          "source": "simulated_path",
          "upper_confidence_price": 762.61
        },
        "3d": {
          "analog_average_price": 692.28,
          "confidence_level": "low",
          "expected_price": 691.84,
          "expected_return": -0.0002,
          "horizon": "3d",
          "lower_confidence_price": 673.08,
          "not_guaranteed_forecast": true,
          "primary_scenario": "bearish_path",
          "primary_scenario_label": "风险路径",
          "primary_scenario_price": 673.08,
          "probability_of_reaching_primary_price": 0.3654,
          "risk_scenario": "bearish_path",
          "risk_scenario_label": "风险路径",
          "risk_scenario_price": 673.08,
          "secondary_scenario": "analog_average_path",
          "secondary_scenario_label": "历史均值情景",
          "secondary_scenario_price": 692.28,
          "source": "simulated_path",
          "upper_confidence_price": 701.92
        },
        "5d": {
          "analog_average_price": 701.71,
          "confidence_level": "low",
          "expected_price": 706.06,
          "expected_return": 0.0204,
          "horizon": "5d",
          "lower_confidence_price": 681.05,
          "not_guaranteed_forecast": true,
          "primary_scenario": "bearish_path",
          "primary_scenario_label": "风险路径",
          "primary_scenario_price": 681.05,
          "probability_of_reaching_primary_price": 0.3654,
          "risk_scenario": "bearish_path",
          "risk_scenario_label": "风险路径",
          "risk_scenario_price": 681.05,
          "secondary_scenario": "analog_average_path",
          "secondary_scenario_label": "历史均值情景",
          "secondary_scenario_price": 701.71,
          "source": "simulated_path",
          "upper_confidence_price": 718.01
        },
        "60d": {
          "analog_average_price": 726.57,
          "confidence_level": "low",
          "expected_price": 745.99,
          "expected_return": 0.0781,
          "horizon": "60d",
          "lower_confidence_price": 646.86,
          "not_guaranteed_forecast": true,
          "primary_scenario": "bearish_path",
          "primary_scenario_label": "风险路径",
          "primary_scenario_price": 646.86,
          "probability_of_reaching_primary_price": 0.3654,
          "risk_scenario": "bearish_path",
          "risk_scenario_label": "风险路径",
          "risk_scenario_price": 646.86,
          "secondary_scenario": "analog_average_path",
          "secondary_scenario_label": "历史均值情景",
          "secondary_scenario_price": 726.57,
          "source": "simulated_path",
          "upper_confidence_price": 793.69
        }
      },
      "horizon_prices": {
        "10d": {
          "analog_average_price": 712.61,
          "confidence": "low",
          "expected_price": 719.47,
          "expected_return": 0.0398,
          "lower_confidence_price": 691.73,
          "not_guaranteed_forecast": true,
          "primary_scenario_price": 691.73,
          "probability_of_reaching_primary_price": 0.3654,
          "risk_scenario_price": 691.73,
          "secondary_scenario_price": 712.61,
          "source": "simulated_path",
          "upper_confidence_price": 733.02
        },
        "1d": {
          "analog_average_price": 689.48,
          "confidence": "low",
          "expected_price": 687.21,
          "expected_return": -0.0069,
          "lower_confidence_price": 680.28,
          "not_guaranteed_forecast": true,
          "primary_scenario_price": 680.28,
          "probability_of_reaching_primary_price": 0.3654,
          "risk_scenario_price": 680.28,
          "secondary_scenario_price": 689.48,
          "source": "simulated_path",
          "upper_confidence_price": 693.63
        },
        "20d": {
          "analog_average_price": 726.24,
          "confidence": "low",
          "expected_price": 737.24,
          "expected_return": 0.0654,
          "lower_confidence_price": 684.75,
          "not_guaranteed_forecast": true,
          "primary_scenario_price": 684.75,
          "probability_of_reaching_primary_price": 0.3654,
          "risk_scenario_price": 684.75,
          "secondary_scenario_price": 726.24,
          "source": "simulated_path",
          "upper_confidence_price": 762.61
        },
        "3d": {
          "analog_average_price": 692.28,
          "confidence": "low",
          "expected_price": 691.84,
          "expected_return": -0.0002,
          "lower_confidence_price": 673.08,
          "not_guaranteed_forecast": true,
          "primary_scenario_price": 673.08,
          "probability_of_reaching_primary_price": 0.3654,
          "risk_scenario_price": 673.08,
          "secondary_scenario_price": 692.28,
          "source": "simulated_path",
          "upper_confidence_price": 701.92
        },
        "5d": {
          "analog_average_price": 701.71,
          "confidence": "low",
          "expected_price": 706.06,
          "expected_return": 0.0204,
          "lower_confidence_price": 681.05,
          "not_guaranteed_forecast": true,
          "primary_scenario_price": 681.05,
          "probability_of_reaching_primary_price": 0.3654,
          "risk_scenario_price": 681.05,
          "secondary_scenario_price": 701.71,
          "source": "simulated_path",
          "upper_confidence_price": 718.01
        },
        "60d": {
          "analog_average_price": 726.57,
          "confidence": "low",
          "expected_price": 745.99,
          "expected_return": 0.0781,
          "lower_confidence_price": 646.86,
          "not_guaranteed_forecast": true,
          "primary_scenario_price": 646.86,
          "probability_of_reaching_primary_price": 0.3654,
          "risk_scenario_price": 646.86,
          "secondary_scenario_price": 726.57,
          "source": "simulated_path",
          "upper_confidence_price": 793.69
        }
      },
      "name": "Nasdaq 100",
      "not_trading_advice": true,
      "path_trigger_levels": {
        "bounce_target_zone": {
          "base_bounce_target": {
            "condition": "基础反抽情景点位，主要来自 20d 反抽路径。",
            "distance_from_current": 70.65,
            "distance_percent": 0.1021,
            "inputs": [
              "bounce_path_20d",
              "primary_path_20d",
              "recent_20d_high"
            ],
            "not_trading_advice": true,
            "price": 762.61,
            "source": "simulated_path"
          },
          "conservative_bounce_target": {
            "condition": "保守反抽情景点位，来自短期反抽路径和近期压力区。",
            "distance_from_current": 26.05,
            "distance_percent": 0.0376,
            "inputs": [
              "bounce_path_5d",
              "recent_5d_high"
            ],
            "not_trading_advice": true,
            "price": 718.01,
            "source": "simulated_path"
          },
          "extended_bounce_target": {
            "condition": "扩展反抽情景点位，来自 60d 反抽路径或上方置信带。",
            "distance_from_current": 101.73,
            "distance_percent": 0.147,
            "inputs": [
              "bounce_path_60d",
              "upper_confidence_band_20d"
            ],
            "not_trading_advice": true,
            "price": 793.69,
            "source": "simulated_path"
          }
        },
        "calculation_note": "Levels are derived from simulated paths, recent price structure, realized-volatility bands and scenario probabilities. They are not trading instructions.",
        "current_price": 691.96,
        "failed_bounce_warning_zone": {
          "critical_warning_level": {
            "condition": "关键警戒区：跌破后风险路径权重显著上升。",
            "distance_from_current": -8.89,
            "distance_percent": -0.0128,
            "inputs": [
              "recent_20d_low",
              "risk_path_10d",
              "lower_confidence_band_20d"
            ],
            "not_trading_advice": true,
            "price": 683.07,
            "source": "simulated_path"
          },
          "first_warning_level": {
            "condition": "第一警戒区：跌破后说明反抽质量变差。",
            "distance_from_current": -18.88,
            "distance_percent": -0.0273,
            "inputs": [
              "recent_5d_low",
              "lower_confidence_band_3d"
            ],
            "not_trading_advice": true,
            "price": 673.08,
            "source": "price_structure"
          }
        },
        "primary_confirmation_level": {
          "condition": "若价格突破或收在该价位上方，说明主路径正在兑现；这不是操作建议。",
          "distance_from_current": 17.01,
          "distance_percent": 0.0246,
          "inputs": [
            "primary_path_5d",
            "recent_5d_high",
            "realized_volatility_band"
          ],
          "not_trading_advice": true,
          "price": 708.97,
          "source": "simulated_path"
        },
        "primary_invalidation_level": {
          "condition": "若价格跌破或收在该价位下方，主路径可信度下降，风险路径权重上升。",
          "distance_from_current": -18.88,
          "distance_percent": -0.0273,
          "inputs": [
            "recent_10d_low",
            "lower_confidence_band_3d",
            "realized_volatility_band"
          ],
          "not_trading_advice": true,
          "price": 673.08,
          "source": "price_structure"
        },
        "primary_probability": 0.3654,
        "primary_scenario": "bearish_path",
        "probability_gap": 0.1085,
        "risk_probability": 0.197,
        "risk_scenario_activation_level": {
          "condition": "若价格跌破该价位，失败反抽 / 下跌延续路径开始接管。",
          "distance_from_current": -8.08,
          "distance_percent": -0.0117,
          "inputs": [
            "risk_path_10d",
            "recent_20d_low",
            "lower_confidence_band_20d"
          ],
          "not_trading_advice": true,
          "price": 683.88,
          "source": "simulated_path"
        },
        "secondary_probability": 0.2569,
        "trend_reversal_confirmation_level": {
          "condition": "若价格突破该价位，趋势修复概率上升；仍需后续前向验证。",
          "distance_from_current": 44.44,
          "distance_percent": 0.0642,
          "inputs": [
            "primary_path_20d",
            "recent_20d_high",
            "20d_or_50d_moving_average"
          ],
          "not_trading_advice": true,
          "price": 736.4,
          "source": "price_structure"
        }
      },
      "price_structure": {
        "atr_proxy_14d": 8.08,
        "data_points": 260,
        "high_10d": 725.51,
        "high_20d": 736.4,
        "high_5d": 708.97,
        "latest_date": "2026-07-23",
        "low_10d": 691.96,
        "low_20d": 691.96,
        "low_5d": 691.96,
        "ma_200d": 642.79,
        "ma_200d_status": "available",
        "ma_20d": 713.32,
        "ma_50d": 718.75,
        "realized_volatility_20d": 0.2368,
        "source": "price_structure",
        "status": "available"
      },
      "primary_probability": 0.3654,
      "primary_scenario": "bearish_path",
      "risk_probability": 0.197,
      "risk_scenario": "bounce_path",
      "secondary_probability": 0.2569,
      "secondary_scenario": "analog_average_path",
      "source_note": "Derived from existing simulated paths, recent price structure and realized-volatility bands.",
      "summary": {
        "plain_language": "QQQ 当前主路径是 失败反抽情景，第二路径是 历史均值情景。价格点位只是路径验证条件，不是操作建议。",
        "primary_confirmation_distance": {
          "distance_from_current": 17.01,
          "distance_percent": 0.0246,
          "price": 708.97
        },
        "primary_invalidation_distance": {
          "distance_from_current": -18.88,
          "distance_percent": -0.0273,
          "price": 673.08
        },
        "risk_activation_distance": {
          "distance_from_current": -8.08,
          "distance_percent": -0.0117,
          "price": 683.88
        }
      },
      "symbol": "QQQ",
      "trigger_levels": {
        "bounce_target_zone": {
          "base": 762.61,
          "conservative": 718.01,
          "extended": 793.69
        },
        "failed_bounce_warning_zone": {
          "critical_warning": 683.07,
          "first_warning": 673.08
        },
        "not_trading_advice": true,
        "primary_confirmation_level": {
          "confidence": "medium",
          "distance_pct": 0.0246,
          "meaning": "若价格突破或收在该价位上方，说明主路径正在兑现；这不是操作建议。",
          "price": 708.97,
          "source": "primary_path_5d + recent_5d_high + realized_volatility_band",
          "source_type": "simulated_path"
        },
        "primary_invalidation_level": {
          "confidence": "medium",
          "distance_pct": -0.0273,
          "meaning": "若价格跌破或收在该价位下方，主路径可信度下降，风险路径权重上升。",
          "price": 673.08,
          "source": "recent_10d_low + lower_confidence_band_3d + realized_volatility_band",
          "source_type": "price_structure"
        },
        "risk_scenario_activation_level": {
          "confidence": "medium",
          "distance_pct": -0.0117,
          "meaning": "若价格跌破该价位，失败反抽 / 下跌延续路径开始接管。",
          "price": 683.88,
          "source": "risk_path_10d + recent_20d_low + lower_confidence_band_20d",
          "source_type": "simulated_path"
        },
        "trend_reversal_confirmation_level": {
          "confidence": "medium",
          "distance_pct": 0.0642,
          "meaning": "若价格突破该价位，趋势修复概率上升；仍需后续前向验证。",
          "price": 736.4,
          "source": "primary_path_20d + recent_20d_high + 20d_or_50d_moving_average",
          "source_type": "price_structure"
        }
      }
    },
    "SPY": {
      "current_price": 738.1799926757812,
      "forecast_price_table": {
        "10d": {
          "analog_average_price": 737.11,
          "confidence_level": "medium",
          "expected_price": 741.63,
          "expected_return": 0.0047,
          "horizon": "10d",
          "lower_confidence_price": 727.28,
          "not_guaranteed_forecast": true,
          "primary_scenario": "bearish_path",
          "primary_scenario_label": "风险路径",
          "primary_scenario_price": 727.28,
          "probability_of_reaching_primary_price": 0.3358,
          "risk_scenario": "bearish_path",
          "risk_scenario_label": "风险路径",
          "risk_scenario_price": 727.28,
          "secondary_scenario": "bounce_path",
          "secondary_scenario_label": "反抽情景",
          "secondary_scenario_price": 748.97,
          "source": "simulated_path",
          "upper_confidence_price": 748.97
        },
        "1d": {
          "analog_average_price": 733.5,
          "confidence_level": "medium",
          "expected_price": 731.59,
          "expected_return": -0.0089,
          "horizon": "1d",
          "lower_confidence_price": 725.44,
          "not_guaranteed_forecast": true,
          "primary_scenario": "bearish_path",
          "primary_scenario_label": "风险路径",
          "primary_scenario_price": 725.44,
          "probability_of_reaching_primary_price": 0.3358,
          "risk_scenario": "bearish_path",
          "risk_scenario_label": "风险路径",
          "risk_scenario_price": 725.44,
          "secondary_scenario": "bounce_path",
          "secondary_scenario_label": "反抽情景",
          "secondary_scenario_price": 738.01,
          "source": "simulated_path",
          "upper_confidence_price": 738.01
        },
        "20d": {
          "analog_average_price": 751.51,
          "confidence_level": "medium",
          "expected_price": 759.53,
          "expected_return": 0.0289,
          "horizon": "20d",
          "lower_confidence_price": 707.18,
          "not_guaranteed_forecast": true,
          "primary_scenario": "bearish_path",
          "primary_scenario_label": "风险路径",
          "primary_scenario_price": 707.18,
          "probability_of_reaching_primary_price": 0.3358,
          "risk_scenario": "bearish_path",
          "risk_scenario_label": "风险路径",
          "risk_scenario_price": 707.18,
          "secondary_scenario": "bounce_path",
          "secondary_scenario_label": "反抽情景",
          "secondary_scenario_price": 785.15,
          "source": "simulated_path",
          "upper_confidence_price": 785.15
        },
        "3d": {
          "analog_average_price": 732.4,
          "confidence_level": "medium",
          "expected_price": 733.46,
          "expected_return": -0.0064,
          "horizon": "3d",
          "lower_confidence_price": 717.19,
          "not_guaranteed_forecast": true,
          "primary_scenario": "bearish_path",
          "primary_scenario_label": "风险路径",
          "primary_scenario_price": 717.19,
          "probability_of_reaching_primary_price": 0.3358,
          "risk_scenario": "bearish_path",
          "risk_scenario_label": "风险路径",
          "risk_scenario_price": 717.19,
          "secondary_scenario": "bounce_path",
          "secondary_scenario_label": "反抽情景",
          "secondary_scenario_price": 742.96,
          "source": "simulated_path",
          "upper_confidence_price": 742.96
        },
        "5d": {
          "analog_average_price": 730.94,
          "confidence_level": "medium",
          "expected_price": 732.01,
          "expected_return": -0.0084,
          "horizon": "5d",
          "lower_confidence_price": 708.79,
          "not_guaranteed_forecast": true,
          "primary_scenario": "bearish_path",
          "primary_scenario_label": "风险路径",
          "primary_scenario_price": 708.79,
          "probability_of_reaching_primary_price": 0.3358,
          "risk_scenario": "bearish_path",
          "risk_scenario_label": "风险路径",
          "risk_scenario_price": 708.79,
          "secondary_scenario": "bounce_path",
          "secondary_scenario_label": "反抽情景",
          "secondary_scenario_price": 743.05,
          "source": "simulated_path",
          "upper_confidence_price": 743.05
        },
        "60d": {
          "analog_average_price": 777.91,
          "confidence_level": "medium",
          "expected_price": 791.13,
          "expected_return": 0.0717,
          "horizon": "60d",
          "lower_confidence_price": 705.65,
          "not_guaranteed_forecast": true,
          "primary_scenario": "bearish_path",
          "primary_scenario_label": "风险路径",
          "primary_scenario_price": 705.65,
          "probability_of_reaching_primary_price": 0.3358,
          "risk_scenario": "bearish_path",
          "risk_scenario_label": "风险路径",
          "risk_scenario_price": 705.65,
          "secondary_scenario": "bounce_path",
          "secondary_scenario_label": "反抽情景",
          "secondary_scenario_price": 833.0,
          "source": "simulated_path",
          "upper_confidence_price": 833.0
        }
      },
      "horizon_prices": {
        "10d": {
          "analog_average_price": 737.11,
          "confidence": "medium",
          "expected_price": 741.63,
          "expected_return": 0.0047,
          "lower_confidence_price": 727.28,
          "not_guaranteed_forecast": true,
          "primary_scenario_price": 727.28,
          "probability_of_reaching_primary_price": 0.3358,
          "risk_scenario_price": 727.28,
          "secondary_scenario_price": 748.97,
          "source": "simulated_path",
          "upper_confidence_price": 748.97
        },
        "1d": {
          "analog_average_price": 733.5,
          "confidence": "medium",
          "expected_price": 731.59,
          "expected_return": -0.0089,
          "lower_confidence_price": 725.44,
          "not_guaranteed_forecast": true,
          "primary_scenario_price": 725.44,
          "probability_of_reaching_primary_price": 0.3358,
          "risk_scenario_price": 725.44,
          "secondary_scenario_price": 738.01,
          "source": "simulated_path",
          "upper_confidence_price": 738.01
        },
        "20d": {
          "analog_average_price": 751.51,
          "confidence": "medium",
          "expected_price": 759.53,
          "expected_return": 0.0289,
          "lower_confidence_price": 707.18,
          "not_guaranteed_forecast": true,
          "primary_scenario_price": 707.18,
          "probability_of_reaching_primary_price": 0.3358,
          "risk_scenario_price": 707.18,
          "secondary_scenario_price": 785.15,
          "source": "simulated_path",
          "upper_confidence_price": 785.15
        },
        "3d": {
          "analog_average_price": 732.4,
          "confidence": "medium",
          "expected_price": 733.46,
          "expected_return": -0.0064,
          "lower_confidence_price": 717.19,
          "not_guaranteed_forecast": true,
          "primary_scenario_price": 717.19,
          "probability_of_reaching_primary_price": 0.3358,
          "risk_scenario_price": 717.19,
          "secondary_scenario_price": 742.96,
          "source": "simulated_path",
          "upper_confidence_price": 742.96
        },
        "5d": {
          "analog_average_price": 730.94,
          "confidence": "medium",
          "expected_price": 732.01,
          "expected_return": -0.0084,
          "lower_confidence_price": 708.79,
          "not_guaranteed_forecast": true,
          "primary_scenario_price": 708.79,
          "probability_of_reaching_primary_price": 0.3358,
          "risk_scenario_price": 708.79,
          "secondary_scenario_price": 743.05,
          "source": "simulated_path",
          "upper_confidence_price": 743.05
        },
        "60d": {
          "analog_average_price": 777.91,
          "confidence": "medium",
          "expected_price": 791.13,
          "expected_return": 0.0717,
          "lower_confidence_price": 705.65,
          "not_guaranteed_forecast": true,
          "primary_scenario_price": 705.65,
          "probability_of_reaching_primary_price": 0.3358,
          "risk_scenario_price": 705.65,
          "secondary_scenario_price": 833.0,
          "source": "simulated_path",
          "upper_confidence_price": 833.0
        }
      },
      "name": "S&P 500",
      "not_trading_advice": true,
      "path_trigger_levels": {
        "bounce_target_zone": {
          "base_bounce_target": {
            "condition": "基础反抽情景点位，主要来自 20d 反抽路径。",
            "distance_from_current": 46.97,
            "distance_percent": 0.0636,
            "inputs": [
              "bounce_path_20d",
              "primary_path_20d",
              "recent_20d_high"
            ],
            "not_trading_advice": true,
            "price": 785.15,
            "source": "simulated_path"
          },
          "conservative_bounce_target": {
            "condition": "保守反抽情景点位，来自短期反抽路径和近期压力区。",
            "distance_from_current": 10.1,
            "distance_percent": 0.0137,
            "inputs": [
              "bounce_path_5d",
              "recent_5d_high"
            ],
            "not_trading_advice": true,
            "price": 748.28,
            "source": "simulated_path"
          },
          "extended_bounce_target": {
            "condition": "扩展反抽情景点位，来自 60d 反抽路径或上方置信带。",
            "distance_from_current": 94.82,
            "distance_percent": 0.1284,
            "inputs": [
              "bounce_path_60d",
              "upper_confidence_band_20d"
            ],
            "not_trading_advice": true,
            "price": 833.0,
            "source": "simulated_path"
          }
        },
        "calculation_note": "Levels are derived from simulated paths, recent price structure, realized-volatility bands and scenario probabilities. They are not trading instructions.",
        "current_price": 738.18,
        "failed_bounce_warning_zone": {
          "critical_warning_level": {
            "condition": "关键警戒区：跌破后风险路径权重显著上升。",
            "distance_from_current": -31.0,
            "distance_percent": -0.042,
            "inputs": [
              "recent_20d_low",
              "risk_path_10d",
              "lower_confidence_band_20d"
            ],
            "not_trading_advice": true,
            "price": 707.18,
            "source": "simulated_path"
          },
          "first_warning_level": {
            "condition": "第一警戒区：跌破后说明反抽质量变差。",
            "distance_from_current": -20.99,
            "distance_percent": -0.0284,
            "inputs": [
              "recent_5d_low",
              "lower_confidence_band_3d"
            ],
            "not_trading_advice": true,
            "price": 717.19,
            "source": "price_structure"
          }
        },
        "primary_confirmation_level": {
          "condition": "若价格突破或收在该价位上方，说明主路径正在兑现；这不是操作建议。",
          "distance_from_current": 10.1,
          "distance_percent": 0.0137,
          "inputs": [
            "primary_path_5d",
            "recent_5d_high",
            "realized_volatility_band"
          ],
          "not_trading_advice": true,
          "price": 748.28,
          "source": "simulated_path"
        },
        "primary_invalidation_level": {
          "condition": "若价格跌破或收在该价位下方，主路径可信度下降，风险路径权重上升。",
          "distance_from_current": -20.99,
          "distance_percent": -0.0284,
          "inputs": [
            "recent_10d_low",
            "lower_confidence_band_3d",
            "realized_volatility_band"
          ],
          "not_trading_advice": true,
          "price": 717.19,
          "source": "price_structure"
        },
        "primary_probability": 0.3358,
        "primary_scenario": "bearish_path",
        "probability_gap": 0.0703,
        "risk_probability": 0.2512,
        "risk_scenario_activation_level": {
          "condition": "若价格跌破该价位，失败反抽 / 下跌延续路径开始接管。",
          "distance_from_current": -31.0,
          "distance_percent": -0.042,
          "inputs": [
            "risk_path_10d",
            "recent_20d_low",
            "lower_confidence_band_20d"
          ],
          "not_trading_advice": true,
          "price": 707.18,
          "source": "simulated_path"
        },
        "secondary_probability": 0.2655,
        "trend_reversal_confirmation_level": {
          "condition": "若价格突破该价位，趋势修复概率上升；仍需后续前向验证。",
          "distance_from_current": 16.77,
          "distance_percent": 0.0227,
          "inputs": [
            "primary_path_20d",
            "recent_20d_high",
            "20d_or_50d_moving_average"
          ],
          "not_trading_advice": true,
          "price": 754.95,
          "source": "price_structure"
        }
      },
      "price_structure": {
        "atr_proxy_14d": 4.39,
        "data_points": 260,
        "high_10d": 754.95,
        "high_20d": 754.95,
        "high_5d": 748.28,
        "latest_date": "2026-07-23",
        "low_10d": 738.18,
        "low_20d": 728.99,
        "low_5d": 738.18,
        "ma_200d": 698.21,
        "ma_200d_status": "available",
        "ma_20d": 745.92,
        "ma_50d": 745.05,
        "realized_volatility_20d": 0.1167,
        "source": "price_structure",
        "status": "available"
      },
      "primary_probability": 0.3358,
      "primary_scenario": "bearish_path",
      "risk_probability": 0.2512,
      "risk_scenario": "analog_average_path",
      "secondary_probability": 0.2655,
      "secondary_scenario": "bounce_path",
      "source_note": "Derived from existing simulated paths, recent price structure and realized-volatility bands.",
      "summary": {
        "plain_language": "SPY 当前主路径是 失败反抽情景，第二路径是 反抽情景。价格点位只是路径验证条件，不是操作建议。",
        "primary_confirmation_distance": {
          "distance_from_current": 10.1,
          "distance_percent": 0.0137,
          "price": 748.28
        },
        "primary_invalidation_distance": {
          "distance_from_current": -20.99,
          "distance_percent": -0.0284,
          "price": 717.19
        },
        "risk_activation_distance": {
          "distance_from_current": -31.0,
          "distance_percent": -0.042,
          "price": 707.18
        }
      },
      "symbol": "SPY",
      "trigger_levels": {
        "bounce_target_zone": {
          "base": 785.15,
          "conservative": 748.28,
          "extended": 833.0
        },
        "failed_bounce_warning_zone": {
          "critical_warning": 707.18,
          "first_warning": 717.19
        },
        "not_trading_advice": true,
        "primary_confirmation_level": {
          "confidence": "medium",
          "distance_pct": 0.0137,
          "meaning": "若价格突破或收在该价位上方，说明主路径正在兑现；这不是操作建议。",
          "price": 748.28,
          "source": "primary_path_5d + recent_5d_high + realized_volatility_band",
          "source_type": "simulated_path"
        },
        "primary_invalidation_level": {
          "confidence": "medium",
          "distance_pct": -0.0284,
          "meaning": "若价格跌破或收在该价位下方，主路径可信度下降，风险路径权重上升。",
          "price": 717.19,
          "source": "recent_10d_low + lower_confidence_band_3d + realized_volatility_band",
          "source_type": "price_structure"
        },
        "risk_scenario_activation_level": {
          "confidence": "medium",
          "distance_pct": -0.042,
          "meaning": "若价格跌破该价位，失败反抽 / 下跌延续路径开始接管。",
          "price": 707.18,
          "source": "risk_path_10d + recent_20d_low + lower_confidence_band_20d",
          "source_type": "simulated_path"
        },
        "trend_reversal_confirmation_level": {
          "confidence": "medium",
          "distance_pct": 0.0227,
          "meaning": "若价格突破该价位，趋势修复概率上升；仍需后续前向验证。",
          "price": 754.95,
          "source": "primary_path_20d + recent_20d_high + 20d_or_50d_moving_average",
          "source_type": "price_structure"
        }
      }
    }
  },
  "validation_type": "daily",
  "version": "forecast_price_levels_v1"
}
